{"monthly_index.md":"93470a87","monthly_202305.md":"89706403","fecommon_webapi_index.md":"69a6b74b","others_线上项目ref.md":"f22891e5","daily_2023_用5分钟配置安全性的server.md":"559e93cd","daily_2023_用vercel部署github_readme_stats.md":"b75d76c7","workflows_tools_tools.md":"6bfab062","fecommon_f_q_index.md":"fbef957d","others_antui.md":"4ce49b2a","daily_index.md":"2149ad4e","fecommon_interface_index.md":"b97e800f","others_juemui.md":"d0ec39d8","others_iconwall.md":"1c0e5ef5","index.md":"da295650","others_index.md":"29554727","others_主页配置ref.md":"8d01bc9e","feframes_uni-app_uni-app中的前后端通信.md":"a4620090","daily_2023_在vitepress中引用组件.md":"ca41e996","feframes_uni-app_uni-app中的常见元素应用.md":"a03a93c1","others_oriui.md":"cc1a2b4f","workflows_index.md":"0e0ac34d","others_静态资源与路径规则.md":"b8a2a3ef","fecommon_program_index.md":"f5897842","fecommon_engineer_vite.md":"11dea705","monthly_202304.md":"f16e760c","others_elementui.md":"543a4d6a","fecommon_js_index.md":"64e08c00"}
