{"09.configure_静态资源与路径规则.md":"f256782a","04.component_elementui.md":"8afba08a","04.component_vitepressui.md":"b7981027","01.monthly_202304.md":"50dea4dc","09.configure_主页配置ref.md":"ed47c002","09.configure_index.md":"359e44c5","01.monthly_index.md":"3962722d","09.configure_线上项目ref.md":"80fe8686","02.tech_用vercel部署github_readme_stats.md":"b255dcec","04.component_antui.md":"309e3d99","02.tech_用5分钟配置安全性的server.md":"1c2f1525","02.tech_index.md":"c5943410","04.component_juemui.md":"cb8e66ed","index.md":"f195db45","01.monthly_月刊demo.md":"09baa1e5","03.interview_index.md":"f5ce46a7"}
